setup.cfg
setup.py
tor_async_couchdb/__init__.py
tor_async_couchdb/async_model_actions.py
tor_async_couchdb/clparserutil.py
tor_async_couchdb/installer.py
tor_async_couchdb/model.py
tor_async_couchdb/retry_strategy.py
tor_async_couchdb/tamper.py
tor_async_couchdb.egg-info/PKG-INFO
tor_async_couchdb.egg-info/SOURCES.txt
tor_async_couchdb.egg-info/dependency_links.txt
tor_async_couchdb.egg-info/requires.txt
tor_async_couchdb.egg-info/top_level.txt