Metadata-Version: 1.1
Name: tor-async-couchdb
Version: 0.50.0
Summary: Tornado Async Client for CouchDB
Home-page: https://github.com/simonsdave/tor-async-couchdb
Author: Dave Simons
Author-email: simonsdave@gmail.com
License: MIT
Download-URL: https://github.com/simonsdave/tor-async-couchdb/tarball/v0.50.0
Keywords: tornado,couchdb
Platform: UNKNOWN
Classifier: Development Status :: 5 - Production/Stable
Classifier: Intended Audience :: Developers
Classifier: Natural Language :: English
Classifier: License :: OSI Approved :: MIT License
Classifier: Operating System :: OS Independent
Classifier: Programming Language :: Python
Classifier: Programming Language :: Python :: 2.7
Classifier: Programming Language :: Python :: Implementation :: CPython
Classifier: Topic :: Software Development :: Libraries :: Python Modules
